{
    "id": 1,
    "published_at": "2020-11-23T20:12:32.832Z",
    "created_at": "2020-11-23T20:12:19.914Z",
    "updated_at": "2020-11-23T20:43:27.800Z",
    "Content": [
        {
            "__component": "page-components.hero",
            "id": 1,
            "title": "GopherCon 2021",
            "cta_url": "/register",
            "cta": "Register Now!",
            "image": {
                "id": 1,
                "name": "0aRpnT1T6WDavN3uuEUl_Banner Website - 1920 x 1080.png",
                "alternativeText": "",
                "caption": "",
                "width": 1920,
                "height": 1080,
                "formats": {
                    "large": {
                        "ext": ".png",
                        "url": "/uploads/large_0a_Rpn_T1_T6_W_Dav_N3uu_E_Ul_Banner_Website_1920_x_1080_df1ded1c7d.png",
                        "hash": "large_0a_Rpn_T1_T6_W_Dav_N3uu_E_Ul_Banner_Website_1920_x_1080_df1ded1c7d",
                        "mime": "image/png",
                        "name": "large_0aRpnT1T6WDavN3uuEUl_Banner Website - 1920 x 1080.png",
                        "path": null,
                        "size": 526.14,
                        "width": 1000,
                        "height": 563
                    },
                    "small": {
                        "ext": ".png",
                        "url": "/uploads/small_0a_Rpn_T1_T6_W_Dav_N3uu_E_Ul_Banner_Website_1920_x_1080_df1ded1c7d.png",
                        "hash": "small_0a_Rpn_T1_T6_W_Dav_N3uu_E_Ul_Banner_Website_1920_x_1080_df1ded1c7d",
                        "mime": "image/png",
                        "name": "small_0aRpnT1T6WDavN3uuEUl_Banner Website - 1920 x 1080.png",
                        "path": null,
                        "size": 198.6,
                        "width": 500,
                        "height": 281
                    },
                    "medium": {
                        "ext": ".png",
                        "url": "/uploads/medium_0a_Rpn_T1_T6_W_Dav_N3uu_E_Ul_Banner_Website_1920_x_1080_df1ded1c7d.png",
                        "hash": "medium_0a_Rpn_T1_T6_W_Dav_N3uu_E_Ul_Banner_Website_1920_x_1080_df1ded1c7d",
                        "mime": "image/png",
                        "name": "medium_0aRpnT1T6WDavN3uuEUl_Banner Website - 1920 x 1080.png",
                        "path": null,
                        "size": 351.11,
                        "width": 750,
                        "height": 422
                    },
                    "thumbnail": {
                        "ext": ".png",
                        "url": "/uploads/thumbnail_0a_Rpn_T1_T6_W_Dav_N3uu_E_Ul_Banner_Website_1920_x_1080_df1ded1c7d.png",
                        "hash": "thumbnail_0a_Rpn_T1_T6_W_Dav_N3uu_E_Ul_Banner_Website_1920_x_1080_df1ded1c7d",
                        "mime": "image/png",
                        "name": "thumbnail_0aRpnT1T6WDavN3uuEUl_Banner Website - 1920 x 1080.png",
                        "path": null,
                        "size": 68.74,
                        "width": 245,
                        "height": 138
                    }
                },
                "hash": "0a_Rpn_T1_T6_W_Dav_N3uu_E_Ul_Banner_Website_1920_x_1080_df1ded1c7d",
                "ext": ".png",
                "mime": "image/png",
                "size": 1005.04,
                "url": "/uploads/0a_Rpn_T1_T6_W_Dav_N3uu_E_Ul_Banner_Website_1920_x_1080_df1ded1c7d.png",
                "previewUrl": null,
                "provider": "local",
                "provider_metadata": null,
                "created_at": "2020-11-23T20:12:08.982Z",
                "updated_at": "2020-11-23T20:12:08.996Z"
            }
        },
        {
            "__component": "page-components.announcement",
            "id": 1,
            "title": "My Announcement",
            "text": "This is big news, folks.",
            "date": "2020-11-23"
        }
    ]
}